Metadata-Version: 2.1
Name: xml-subsetter
Version: 0.0.2
Summary: decimate xml data while keeping others intact 
Home-page: https://github.com/Madoshakalaka/xml-subsetter
Author: Matt Yan
Author-email: syan4@ualberta.ca
License: UNKNOWN
Project-URL: Bug Reports, https://github.com/Madoshakalaka/xml-subsetter/issues
Project-URL: Funding, https://github.com/Madoshakalaka/xml-subsetter
Project-URL: Say Thanks!, https://github.com/Madoshakalaka/xml-subsetter
Project-URL: Source, https://github.com/Madoshakalaka/xml-subsetter
Platform: UNKNOWN
Classifier: Development Status :: 5 - Production/Stable
Classifier: Intended Audience :: Developers
Classifier: Topic :: Software Development :: Build Tools
Classifier: License :: OSI Approved :: MIT License
Classifier: Programming Language :: Python :: 3.5
Classifier: Programming Language :: Python :: 3.6
Classifier: Programming Language :: Python :: 3.7
Requires-Python: >=3.5
Provides-Extra: dev
